pytorch_fanatics/__init__.py
pytorch_fanatics/dataloader/__init__.py
pytorch_fanatics/dataloader/loader.py
pytorch_fanatics/logger/Logger.py
pytorch_fanatics/logger/__init__.py
pytorch_fanatics/trainer/Trainer.py
pytorch_fanatics/trainer/__init__.py
pytorch_fanatics/utils/EarlyStop.py
pytorch_fanatics/utils/LRFinder.py
pytorch_fanatics/utils/Saver.py
pytorch_fanatics/utils/__init__.py
pytorch_fanatics-0.2.7.dist-info/LICENSE.txt
pytorch_fanatics-0.2.7.dist-info/METADATA
pytorch_fanatics-0.2.7.dist-info/WHEEL
pytorch_fanatics-0.2.7.dist-info/top_level.txt
pytorch_fanatics-0.2.7.dist-info/RECORD
