Metadata-Version: 2.1
Name: pytorch-fanatics
Version: 0.2.7
Summary: A new library for Computer Vision
Home-page: https://github.com/MiHarsh/pytorch_fanatics
Author: Harsh Mishra and Tanish Gupta
Author-email: harshm17172612@gmail.com
License: MIT License
Platform: linux
Platform: unix
Requires-Python: >3.5.2
Requires-Dist: scikit-learn (>=0.22.1)
